mips_tamu/tags/lab3/hw/DataMemory.v
`ifndef _datamemory_v_
`define _datamemory_v_
`endif



module DataMemory ( ReadData , Address , WriteData , MemoryRead , MemoryWrite , Clock ) ;

  parameter DataMemory_Size = 256;              // in bytes

  output reg [31:0] ReadData;
  input wire [5:0] Address; 
  input wire [31:0] WriteData;
  input wire MemoryRead, MemoryWrite, Clock;
  
  reg [31:0] data [DataMemory_Size/4:0];        // The actual stored data
  
  always @(*) begin                             
    if (MemoryRead)
      ReadData <= data[Address];                
    else
      ReadData <= ReadData;                     // If read enable is low, retain previous value
  
  end
  
  always @(negedge Clock) begin                  // Writes synchronous with negedge Clock
    if (MemoryWrite)
      data[Address] <= WriteData;  
  end  
    

endmodule

mips_tamu/tags/lab7/test/DataMemoryTest.v
`include "hw/DataMemory.v"

`timescale 1ns / 1ps

`define STRLEN 32
module DataMemoryTest_v;


	task passTest;
		input [31:0] actualOut, expectedOut;
		input [`STRLEN*8:0] testType;
		inout [7:0] passed;
	
		if(actualOut == expectedOut) begin $display ("%s passed", testType); passed = passed + 1; end
		else $display ("%s failed: %d should be %d", testType, actualOut, expectedOut);
	endtask
	
	task allPassed;
		input [7:0] passed;
		input [7:0] numTests;
		
		if(passed == numTests) $display ("All tests passed");
		else $display("Some tests failed");
	endtask


	// Inputs
	reg [31:0] Address;
	reg [31:0] WriteData;
	reg MemoryRead;
	reg MemoryWrite;
	reg Clock;
	reg [7:0] passed;

   //intermediate nets
	wire [5:0] MemAddress;

	// Outputs
	wire [31:0] ReadData;

	assign MemAddress = Address[7:2];

	// Instantiate the Unit Under Test (UUT)
	DataMemory uut (
		.ReadData(ReadData), 
		.Address(MemAddress), 
		.WriteData(WriteData), 
		.MemoryRead(MemoryRead), 
		.MemoryWrite(MemoryWrite), 
		.Clock(Clock)
	);

	initial begin
		// Initialize Inputs
		$dumpfile("test.vcd");
		$dumpvars(0, DataMemoryTest_v);
		Address = 0;
		WriteData = 0;
		MemoryRead = 0;
		MemoryWrite = 0;
		Clock = 0;
		passed = 0;

		// Add stimulus here
		$display("Init Memory with some useful data");
		#50 Clock = 1;{Address, WriteData, MemoryWrite, MemoryRead} = {32'h0, 32'h4, 2'h2};#50 Clock = 0;
		#50 Clock = 1;{Address, WriteData, MemoryWrite, MemoryRead} = {32'h4, 32'h3, 2'h2};#50 Clock = 0;
		#50 Clock = 1;{Address, WriteData, MemoryWrite, MemoryRead} = {32'h8, 32'd50, 2'h2};#50 Clock = 0;
		#50 Clock = 1;{Address, WriteData, MemoryWrite, MemoryRead} = {32'hc, 32'd40, 2'h2};#50 Clock = 0;
		#50 Clock = 1;{Address, WriteData, MemoryWrite, MemoryRead} = {32'h10, 32'd30, 2'h2};#50 Clock = 0;
		#50 Clock = 1;{Address, WriteData, MemoryWrite, MemoryRead} = {32'h14, 32'h0, 2'h2};#50 Clock = 0;
		#50 Clock = 1;{Address, WriteData, MemoryWrite, MemoryRead} = {32'h20, 32'h0, 2'h2};#50 Clock = 0;
		#50 Clock = 1;{Address, WriteData, MemoryWrite, MemoryRead} = {32'h78, 32'h132, 2'h2};#50 Clock = 0;
		#50 Clock = 1;{Address, WriteData, MemoryWrite, MemoryRead} = {32'h80, 32'd16435934, 2'h2};#50 Clock = 0;
		#50 Clock = 1;{Address, WriteData, MemoryWrite, MemoryRead} = {32'hc8, 32'haaaaffff, 2'h2};#50 Clock = 0;
		#50 Clock = 1;{Address, WriteData, MemoryWrite, MemoryRead} = {32'hcc, 32'd1431699200, 2'h2};#50 Clock = 0;
		#50 Clock = 1;{Address, WriteData, MemoryWrite, MemoryRead} = {32'hf0, 32'hffff0000, 2'h2};#50 Clock = 0;

		#50 Clock = 1;
		
		{Address, WriteData, MemoryWrite, MemoryRead} = {32'h14, 32'hffff0000, 2'h1};
		#50 Clock = 0;
		#50 Clock = 1;
		passTest(ReadData, 32'h0, "Read address 0x14", passed);
		
		{Address, WriteData, MemoryWrite, MemoryRead} = {32'hf0, 32'hffff0000, 2'h1};
		#50 Clock = 0;
		#50 Clock = 1;
		passTest(ReadData, 32'hffff0000, "Read address 0xf0", passed);
		
		{Address, WriteData, MemoryWrite, MemoryRead} = {32'hcc, 32'hffff0000, 2'h1};
		#50 Clock = 0;
		#50 Clock = 1;
		passTest(ReadData, 32'd1431699200, "Read address 0xcc", passed);
		
		{Address, WriteData, MemoryWrite, MemoryRead} = {32'hc8, 32'hffff0000, 2'h1};
		#50 Clock = 0;
		#50 Clock = 1;
		passTest(ReadData, 32'haaaaffff, "Read address 0xc8", passed);
		
		{Address, WriteData, MemoryWrite, MemoryRead} = {32'hc, 32'hffff0000, 2'h1};
		#50 Clock = 0;
		#50 Clock = 1;
		passTest(ReadData, 32'd40, "Read address 0xc", passed);
		
		
		
		{Address, WriteData, MemoryWrite, MemoryRead} = {32'hc8, 32'hffff0000, 2'h0};
        #50 Clock = 0;
        #50 Clock = 1;
        passTest(ReadData, 32'haaaaffff, "Read address 0xc8", passed);
        
        {Address, WriteData, MemoryWrite, MemoryRead} = {32'hc, 32'hffff0000, 2'h0};
        #50 Clock = 0;
        #50 Clock = 1;
        passTest(ReadData, 32'd40, "Read address 0xc", passed);
		
		allPassed(passed, 7);
		$finish;

	end
      
endmodule

mips_tamu/tags/lab4/test.vcd
$date
	Sun May 05 21:47:23 2013
$end
$version
	Icarus Verilog
$end
$timescale
	1ps
$end
$scope module DataMemoryTest_v $end
$var wire 6 ! MemAddress [5:0] $end
$var wire 32 " ReadData [31:0] $end
$var reg 32 # Address [31:0] $end
$var reg 1 $ Clock $end
$var reg 1 % MemoryRead $end
$var reg 1 & MemoryWrite $end
$var reg 32 ' WriteData [31:0] $end
$var reg 8 ( passed [7:0] $end
$scope module uut $end
$var wire 6 ) Address [5:0] $end
$var wire 1 * Clock $end
$var wire 1 + MemoryRead $end
$var wire 1 , MemoryWrite $end
$var wire 32 - WriteData [31:0] $end
$var reg 32 . ReadData [31:0] $end
$upscope $end
$scope task allPassed $end
$var reg 8 / numTests [7:0] $end
$var reg 8 0 passed [7:0] $end
$upscope $end
$scope task passTest $end
$var reg 32 1 actualOut [31:0] $end
$var reg 32 2 expectedOut [31:0] $end
$var reg 8 3 passed [7:0] $end
$var reg 257 4 testType [256:0] $end
$upscope $end
$upscope $end
$enddefinitions $end
#0
$dumpvars
bx 4
bx 3
bx 2
bx 1
bx 0
bx /
bx .
b0 -
0,
0+
0*
b0 )
b0 (
b0 '
0&
0%
0$
b0 #
bx "
b0 !
$end
#50000
b100 '
b100 -
1&
1,
1$
1*
#100000
0$
0*
#150000
b1 !
b1 )
b100 #
b11 '
b11 -
1$
1*
#200000
0$
0*
#250000
b10 !
b10 )
b1000 #
b110010 '
b110010 -
1$
1*
#300000
0$
0*
#350000
b11 !
b11 )
b1100 #
b101000 '
b101000 -
1$
1*
#400000
0$
0*
#450000
b100 !
b100 )
b10000 #
b11110 '
b11110 -
1$
1*
#500000
0$
0*
#550000
b101 !
b101 )
b10100 #
b0 '
b0 -
1$
1*
#600000
0$
0*
#650000
b1000 !
b1000 )
b100000 #
1$
1*
#700000
0$
0*
#750000
b11110 !
b11110 )
b1111000 #
b100110010 '
b100110010 -
1$
1*
#800000
0$
0*
#850000
b100000 !
b100000 )
b10000000 #
b111110101100101011011110 '
b111110101100101011011110 -
1$
1*
#900000
0$
0*
#950000
b110010 !
b110010 )
b11001000 #
b10101010101010101111111111111111 '
b10101010101010101111111111111111 -
1$
1*
#1000000
0$
0*
#1050000
b110011 !
b110011 )
b11001100 #
b1010101010101011111111100000000 '
b1010101010101011111111100000000 -
1$
1*
#1100000
0$
0*
#1150000
b111100 !
b111100 )
b11110000 #
b11111111111111110000000000000000 '
b11111111111111110000000000000000 -
1$
1*
#1200000
0$
0*
#1250000
b0 .
b0 "
b101 !
b101 )
b10100 #
0&
0,
1%
1+
1$
1*
#1300000
0$
0*
#1350000
b11111111111111110000000000000000 .
b11111111111111110000000000000000 "
b111100 !
b111100 )
b11110000 #
b1 (
b1 3
b101001001100101011000010110010000100000011000010110010001100100011100100110010101110011011100110010000000110000011110000011000100110100 4
b0 2
b0 1
1$
1*
#1400000
0$
0*
#1450000
b1010101010101011111111100000000 .
b1010101010101011111111100000000 "
b110011 !
b110011 )
b11001100 #
b10 (
b10 3
b101001001100101011000010110010000100000011000010110010001100100011100100110010101110011011100110010000000110000011110000110011000110000 4
b11111111111111110000000000000000 2
b11111111111111110000000000000000 1
1$
1*
#1500000
0$
0*
#1550000
b10101010101010101111111111111111 .
b10101010101010101111111111111111 "
b110010 !
b110010 )
b11001000 #
b11 (
b11 3
b101001001100101011000010110010000100000011000010110010001100100011100100110010101110011011100110010000000110000011110000110001101100011 4
b1010101010101011111111100000000 2
b1010101010101011111111100000000 1
1$
1*
#1600000
0$
0*
#1650000
b101000 .
b101000 "
b11 !
b11 )
b1100 #
b100 (
b100 3
b101001001100101011000010110010000100000011000010110010001100100011100100110010101110011011100110010000000110000011110000110001100111000 4
b10101010101010101111111111111111 2
b10101010101010101111111111111111 1
1$
1*
#1700000
0$
0*
#1750000
b110010 !
b110010 )
b11001000 #
0%
0+
b101 (
b101 3
b1010010011001010110000101100100001000000110000101100100011001000111001001100101011100110111001100100000001100000111100001100011 4
b101000 2
b101000 1
1$
1*
#1800000
0$
0*
#1850000
b11 !
b11 )
b1100 #
b101001001100101011000010110010000100000011000010110010001100100011100100110010101110011011100110010000000110000011110000110001100111000 4
b10101010101010101111111111111111 2
1$
1*
#1900000
0$
0*
#1950000
b111 /
b110 0
b110 (
b110 3
b1010010011001010110000101100100001000000110000101100100011001000111001001100101011100110111001100100000001100000111100001100011 4
b101000 2
1$
1*
